fixman/__init__.py
fixman/hook.py
FixMan-0.0.0.dev248.dist-info/METADATA
FixMan-0.0.0.dev248.dist-info/WHEEL
FixMan-0.0.0.dev248.dist-info/top_level.txt
FixMan-0.0.0.dev248.dist-info/RECORD
