Metadata-Version: 2.1
Name: FixMan
Version: 0.0.0.dev248
Requires-Python: >=3.10
Requires-Dist: pre-commit ==3.3.3
Requires-Dist: gittidy
Requires-Dist: markitup
Requires-Dist: loggerman
Requires-Dist: pyserials
Requires-Dist: PyShellMan
